{
  "Like-Logs": "ログイン",
  "Time": "タイムタイム",
  "Text": "テキスト",
  "Statistics": "統計データ",
  "Skills": "スキル",
  "Attributes": "アトリビュート",
  "Two-Handed": "2手作業",
  "Health": "健康保健",
  "Light Armor": "軽い装甲",
  "Alteration": "アルテレーション",
  "Stamina": "スタミナ",
  "Restoration": "レクリエーション",
  "Block": "ブロック",
  "Magicka": "マジックカ",
  "Armor": "アーマー",
  "Location": "アクセス",
  "Status": "ステータス",
  "Level": "レベル",
  "Favor": "お気に入り",
  "Is current Follower": "現在のフォロワー",
  "Current Race": "現在のレース",
  "Last seen in": "最近見ました",
  "Words of Power heard": "聞いた電力の単語",
  "Words of Power used": "使用される電力の単語",
  "Inventory": "インベントリ",
  "Cuirass": "クレアス",
  "Comment rate": "コメント率",
  "Gloves": "グローブ",
  "Boots": "ブーツ",
  "Weapons": "フィードバック",
  "Greatsword": "グレートソード",
  "Potions": "ポテト",
  "Health 1": "健康 1",
  "Health 2": "健康 2",
  "Health 3": "健康 3",
  "Health 4": "健康 4",
  "Health 5": "健康 5",
  "Health 6": "健康 6",
  "Food": "フード",
  "Wolf's Feed": "Wolfのフィード",
  "Blood Potion": "血のPotion",
  "Settings": "コンテンツ",
  "xVASynth": "xVAシンス",
  "Idrinth's Comments": "Idrinthのコメント",
  "Enable comments": "コメントを有効にする",
  "Scripts": "スクリプト",
  "Disable automatic redressing": "無効な自動resdressing",
  "Search and Find": "検索と検索",
  "Enable search quest": "検索クエストを有効にする",
  "Enable XvaSynth Scenes": "XvaSynth シーンを有効にする",
  "Current Wolf Count": "現在のWolfカウント",
  "Speaking chance of Wolves": "Wolvesのチャンスを話す",
  "Disable Wolf summoning": "無効なWolf召喚",
  "Damage rate": "ダメージ率",
  "Debug": "デブグ",
  "Once Closed": "休診日",
  "Now": "詳しくはこちら",
  "Reevaluate AI-Packages": "AIパッケージの評価",
  "On Close": "閉じる",
  "Teleport to Player": "プレーヤーへの通信",
  "Stop Combat": "戦闘停止",
  "Interrupt Now": "今すぐ申し込む",
  "Remove Wolves": "Wolvesを削除する",
  "All Now": "詳しくはこちら",
  "Unlock movement": "ロック解除",
  "Assassin Spawn Rate": "アスサシン スパン レート",
  "Destruction": "デザート",
  "NPC Comment Rate": "NPCのコメント率"
}